scibot/streamer.py
scibot/telebot.py
scibot/tools.py
scibot/what_a_c.py
scienceBot-0.1.1.1.dist-info/METADATA
scienceBot-0.1.1.1.dist-info/WHEEL
scienceBot-0.1.1.1.dist-info/entry_points.txt
scienceBot-0.1.1.1.dist-info/top_level.txt
scienceBot-0.1.1.1.dist-info/RECORD
