Metadata-Version: 2.1
Name: scienceBot
Version: 0.1.1.1
Summary: Bot for sci-com and policy-com 
Home-page: https://github.com/fanasal/science_bot
License: GNU Affero General Public License v3.0
Keywords: psychedelics,fact-checking,sci-com,drug policy,research,science
Platform: UNKNOWN
Requires-Dist: beautifulsoup4 (==4.9.3)
Requires-Dist: feedparser (==6.0.2)
Requires-Dist: oauthlib (==3.1.1)
Requires-Dist: python-dotenv (==0.15.0)
Requires-Dist: requests (==2.26)
Requires-Dist: requests-oauthlib (==1.3.0)
Requires-Dist: schedule (==0.6.0)
Requires-Dist: telebot (==0.0.4)
Requires-Dist: Telethon (==1.18.2)
Requires-Dist: tweepy (==4.4.0)
Requires-Dist: urllib3 (==1.26.7)
